sentier_glossary/__init__.py
sentier_glossary/main.py
sentier_glossary/settings.py
sentier_glossary-0.5.2.dist-info/LICENSE
sentier_glossary-0.5.2.dist-info/METADATA
sentier_glossary-0.5.2.dist-info/WHEEL
sentier_glossary-0.5.2.dist-info/top_level.txt
sentier_glossary-0.5.2.dist-info/RECORD
