Metadata-Version: 2.1
Name: sentier_glossary
Version: 0.5.2
Summary: Client interface to sentier.dev sustainability assessment glossary
Author-email: João Gonçalves <jsvgoncalves@gmail.com>, Chris Mutel <cmutel@gmail.com>
Maintainer-email: João Gonçalves <jsvgoncalves@gmail.com>, Chris Mutel <cmutel@gmail.com>
Project-URL: source, https://github.com/Depart-de-Sentier/sentier_glossary
Project-URL: homepage, https://github.com/Depart-de-Sentier/sentier_glossary
Project-URL: tracker, https://github.com/Depart-de-Sentier/sentier_glossary/issues
Classifier: Development Status :: 4 - Beta
Classifier: Programming Language :: Python
Classifier: Programming Language :: Python :: 3
Classifier: Programming Language :: Python :: 3.10
Classifier: Programming Language :: Python :: 3.11
Classifier: Programming Language :: Python :: 3.12
Classifier: Natural Language :: English
Classifier: Operating System :: OS Independent
Classifier: Topic :: Scientific/Engineering
Requires-Python: >=3.10
License-File: LICENSE
Requires-Dist: pydantic-settings
Requires-Dist: requests
Requires-Dist: sentence-transformers
Requires-Dist: torch
Requires-Dist: pandas
Provides-Extra: dev
Requires-Dist: build ; extra == 'dev'
Requires-Dist: pre-commit ; extra == 'dev'
Requires-Dist: pylint ; extra == 'dev'
Requires-Dist: pytest ; extra == 'dev'
Requires-Dist: pytest-cov ; extra == 'dev'
Requires-Dist: pytest-randomly ; extra == 'dev'
Requires-Dist: setuptools ; extra == 'dev'
Requires-Dist: types-requests ; extra == 'dev'
Provides-Extra: testing
Requires-Dist: sentier-glossary ; extra == 'testing'
Requires-Dist: pytest ; extra == 'testing'
Requires-Dist: pytest-cov ; extra == 'testing'
Requires-Dist: python-coveralls ; extra == 'testing'
